MANIFEST.in
README.txt
setup.cfg
setup.py
conf/__init__.py
conf/css_crawler.cfg
css_crawler/__init__.py
css_crawler/app.py
css_crawler/models.py
css_crawler.egg-info/PKG-INFO
css_crawler.egg-info/SOURCES.txt
css_crawler.egg-info/dependency_links.txt
css_crawler.egg-info/entry_points.txt
css_crawler.egg-info/not-zip-safe
css_crawler.egg-info/requires.txt
css_crawler.egg-info/top_level.txt
css_crawler/lib/__init__.py
css_crawler/lib/i18n.py
css_crawler/lib/log.py
css_crawler/lib/short_url.py
css_crawler/lib/validator.py
css_crawler/lib/css/__init__.py
css_crawler/lib/css/capture.py
css_crawler/lib/css/extract.py
css_crawler/lib/css/fetch.py
css_crawler/tests/__init__.py
css_crawler/tests/helpers.py
css_crawler/tests/test_csscapture.py
css_crawler/tests/test_cssextract.py
css_crawler/tests/test_urljoin.py
css_crawler/tests/test_validator.py
css_crawler/ui/__init__.py
css_crawler/ui/colorpalette/__init__.py
css_crawler/ui/colorpalette/component.py
css_crawler/ui/colorpalette/view.py
css_crawler/ui/tagcloud/__init__.py
css_crawler/ui/tagcloud/component.py
css_crawler/ui/tagcloud/view.py
css_crawler/ui/urlfetcher/__init__.py
css_crawler/ui/urlfetcher/component.py
css_crawler/ui/urlfetcher/view.py
data/__init__.py
static/__init__.py
static/css/stylesheet.css
static/images/arrow-left.png
static/images/browser-globe-download.png
static/images/css.jpg
static/images/logo_nagare.png
static/images/logo_nng.png
static/images/trash.png
static/js/script.js