Metadata-Version: 1.0
Name: css-crawler
Version: 0.0.5
Summary: CSSCrawler is a Nagare application that parses CSSstyles from website URL and generate a color palette.
Home-page: https://bitbucket.org/Alzakath/csscrawler
Author: Herve Coatanhay
Author-email: herve.coatanhay@gmail.com
License: BSD
Keywords: Nagare CSS
Platform: UNKNOWN
Classifier: Programming Language :: Python :: 2.6
Classifier: Programming Language :: Python :: 2.7
Classifier: Programming Language :: Python :: Implementation :: Stackless
